[
  { "countryCode": "AF", "country": "Afghanistan" },
  { "countryCode": "AX", "country": "Åland Islands" },
  { "countryCode": "AL", "country": "Albania" },
  { "countryCode": "DZ", "country": "Algeria" },
  { "countryCode": "AS", "country": "American Samoa" },
  { "countryCode": "AD", "country": "Andorra" },
  { "countryCode": "AO", "country": "Angola" },
  { "countryCode": "AI", "country": "Anguilla" },
  { "countryCode": "AQ", "country": "Antarctica" },
  { "countryCode": "AG", "country": "Antigua & Barbuda" },
  { "countryCode": "AR", "country": "Argentina" },
  { "countryCode": "AM", "country": "Armenia" },
  { "countryCode": "AW", "country": "Aruba" },
  { "countryCode": "AC", "country": "Ascension Island" },
  { "countryCode": "AU", "country": "Australia" },
  { "countryCode": "AT", "country": "Austria" },
  { "countryCode": "AZ", "country": "Azerbaijan" },
  { "countryCode": "BS", "country": "Bahamas" },
  { "countryCode": "BH", "country": "Bahrain" },
  { "countryCode": "BD", "country": "Bangladesh" },
  { "countryCode": "BB", "country": "Barbados" },
  { "countryCode": "BY", "country": "Belarus" },
  { "countryCode": "BE", "country": "Belgium" },
  { "countryCode": "BZ", "country": "Belize" },
  { "countryCode": "BJ", "country": "Benin" },
  { "countryCode": "BM", "country": "Bermuda" },
  { "countryCode": "BT", "country": "Bhutan" },
  { "countryCode": "BO", "country": "Bolivia" },
  { "countryCode": "BA", "country": "Bosnia & Herzegovina" },
  { "countryCode": "BW", "country": "Botswana" },
  { "countryCode": "BR", "country": "Brazil" },
  { "countryCode": "IO", "country": "British Indian Ocean Territory" },
  { "countryCode": "VG", "country": "British Virgin Islands" },
  { "countryCode": "BN", "country": "Brunei" },
  { "countryCode": "BG", "country": "Bulgaria" },
  { "countryCode": "BF", "country": "Burkina Faso" },
  { "countryCode": "BI", "country": "Burundi" },
  { "countryCode": "KH", "country": "Cambodia" },
  { "countryCode": "CM", "country": "Cameroon" },
  { "countryCode": "CA", "country": "Canada" },
  { "countryCode": "IC", "country": "Canary Islands" },
  { "countryCode": "CV", "country": "Cape Verde" },
  { "countryCode": "BQ", "country": "Caribbean Netherlands" },
  { "countryCode": "KY", "country": "Cayman Islands" },
  { "countryCode": "CF", "country": "Central African Republic" },
  { "countryCode": "EA", "country": "Ceuta & Melilla" },
  { "countryCode": "TD", "country": "Chad" },
  { "countryCode": "CL", "country": "Chile" },
  { "countryCode": "CN", "country": "China" },
  { "countryCode": "CX", "country": "Christmas Island" },
  { "countryCode": "CC", "country": "Cocos (Keeling) Islands" },
  { "countryCode": "CO", "country": "Colombia" },
  { "countryCode": "KM", "country": "Comoros" },
  { "countryCode": "CG", "country": "Congo - Brazzaville" },
  { "countryCode": "CD", "country": "Congo - Kinshasa" },
  { "countryCode": "CK", "country": "Cook Islands" },
  { "countryCode": "CR", "country": "Costa Rica" },
  { "countryCode": "CI", "country": "Côte d’Ivoire" },
  { "countryCode": "HR", "country": "Croatia" },
  { "countryCode": "CU", "country": "Cuba" },
  { "countryCode": "CW", "country": "Curaçao" },
  { "countryCode": "CY", "country": "Cyprus" },
  { "countryCode": "CZ", "country": "Czechia" },
  { "countryCode": "DK", "country": "Denmark" },
  { "countryCode": "DG", "country": "Diego Garcia" },
  { "countryCode": "DJ", "country": "Djibouti" },
  { "countryCode": "DM", "country": "Dominica" },
  { "countryCode": "DO", "country": "Dominican Republic" },
  { "countryCode": "EC", "country": "Ecuador" },
  { "countryCode": "EG", "country": "Egypt" },
  { "countryCode": "SV", "country": "El Salvador" },
  { "countryCode": "GQ", "country": "Equatorial Guinea" },
  { "countryCode": "ER", "country": "Eritrea" },
  { "countryCode": "EE", "country": "Estonia" },
  { "countryCode": "SZ", "country": "Eswatini" },
  { "countryCode": "ET", "country": "Ethiopia" },
  { "countryCode": "FK", "country": "Falkland Islands" },
  { "countryCode": "FO", "country": "Faroe Islands" },
  { "countryCode": "FJ", "country": "Fiji" },
  { "countryCode": "FI", "country": "Finland" },
  { "countryCode": "FR", "country": "France" },
  { "countryCode": "GF", "country": "French Guiana" },
  { "countryCode": "PF", "country": "French Polynesia" },
  { "countryCode": "TF", "country": "French Southern Territories" },
  { "countryCode": "GA", "country": "Gabon" },
  { "countryCode": "GM", "country": "Gambia" },
  { "countryCode": "GE", "country": "Georgia" },
  { "countryCode": "DE", "country": "Germany" },
  { "countryCode": "GH", "country": "Ghana" },
  { "countryCode": "GI", "country": "Gibraltar" },
  { "countryCode": "GR", "country": "Greece" },
  { "countryCode": "GL", "country": "Greenland" },
  { "countryCode": "GD", "country": "Grenada" },
  { "countryCode": "GP", "country": "Guadeloupe" },
  { "countryCode": "GU", "country": "Guam" },
  { "countryCode": "GT", "country": "Guatemala" },
  { "countryCode": "GG", "country": "Guernsey" },
  { "countryCode": "GN", "country": "Guinea" },
  { "countryCode": "GW", "country": "Guinea-Bissau" },
  { "countryCode": "GY", "country": "Guyana" },
  { "countryCode": "HT", "country": "Haiti" },
  { "countryCode": "HN", "country": "Honduras" },
  { "countryCode": "HK", "country": "Hong Kong SAR China" },
  { "countryCode": "HU", "country": "Hungary" },
  { "countryCode": "IS", "country": "Iceland" },
  { "countryCode": "IN", "country": "India" },
  { "countryCode": "ID", "country": "Indonesia" },
  { "countryCode": "IR", "country": "Iran" },
  { "countryCode": "IQ", "country": "Iraq" },
  { "countryCode": "IE", "country": "Ireland" },
  { "countryCode": "IM", "country": "Isle of Man" },
  { "countryCode": "IL", "country": "Israel" },
  { "countryCode": "IT", "country": "Italy" },
  { "countryCode": "JM", "country": "Jamaica" },
  { "countryCode": "JP", "country": "Japan" },
  { "countryCode": "JE", "country": "Jersey" },
  { "countryCode": "JO", "country": "Jordan" },
  { "countryCode": "KZ", "country": "Kazakhstan" },
  { "countryCode": "KE", "country": "Kenya" },
  { "countryCode": "KI", "country": "Kiribati" },
  { "countryCode": "XK", "country": "Kosovo" },
  { "countryCode": "KW", "country": "Kuwait" },
  { "countryCode": "KG", "country": "Kyrgyzstan" },
  { "countryCode": "LA", "country": "Laos" },
  { "countryCode": "LV", "country": "Latvia" },
  { "countryCode": "LB", "country": "Lebanon" },
  { "countryCode": "LS", "country": "Lesotho" },
  { "countryCode": "LR", "country": "Liberia" },
  { "countryCode": "LY", "country": "Libya" },
  { "countryCode": "LI", "country": "Liechtenstein" },
  { "countryCode": "LT", "country": "Lithuania" },
  { "countryCode": "LU", "country": "Luxembourg" },
  { "countryCode": "MO", "country": "Macao SAR China" },
  { "countryCode": "MG", "country": "Madagascar" },
  { "countryCode": "MW", "country": "Malawi" },
  { "countryCode": "MY", "country": "Malaysia" },
  { "countryCode": "MV", "country": "Maldives" },
  { "countryCode": "ML", "country": "Mali" },
  { "countryCode": "MT", "country": "Malta" },
  { "countryCode": "MH", "country": "Marshall Islands" },
  { "countryCode": "MQ", "country": "Martinique" },
  { "countryCode": "MR", "country": "Mauritania" },
  { "countryCode": "MU", "country": "Mauritius" },
  { "countryCode": "YT", "country": "Mayotte" },
  { "countryCode": "MX", "country": "Mexico" },
  { "countryCode": "FM", "country": "Micronesia" },
  { "countryCode": "MD", "country": "Moldova" },
  { "countryCode": "MC", "country": "Monaco" },
  { "countryCode": "MN", "country": "Mongolia" },
  { "countryCode": "ME", "country": "Montenegro" },
  { "countryCode": "MS", "country": "Montserrat" },
  { "countryCode": "MA", "country": "Morocco" },
  { "countryCode": "MZ", "country": "Mozambique" },
  { "countryCode": "MM", "country": "Myanmar (Burma)" },
  { "countryCode": "NA", "country": "Namibia" },
  { "countryCode": "NR", "country": "Nauru" },
  { "countryCode": "NP", "country": "Nepal" },
  { "countryCode": "NL", "country": "Netherlands" },
  { "countryCode": "NC", "country": "New Caledonia" },
  { "countryCode": "NZ", "country": "New Zealand" },
  { "countryCode": "NI", "country": "Nicaragua" },
  { "countryCode": "NE", "country": "Niger" },
  { "countryCode": "NG", "country": "Nigeria" },
  { "countryCode": "NU", "country": "Niue" },
  { "countryCode": "NF", "country": "Norfolk Island" },
  { "countryCode": "KP", "country": "North Korea" },
  { "countryCode": "MK", "country": "North Macedonia" },
  { "countryCode": "MP", "country": "Northern Mariana Islands" },
  { "countryCode": "NO", "country": "Norway" },
  { "countryCode": "OM", "country": "Oman" },
  { "countryCode": "PK", "country": "Pakistan" },
  { "countryCode": "PW", "country": "Palau" },
  { "countryCode": "PS", "country": "Palestinian Territories" },
  { "countryCode": "PA", "country": "Panama" },
  { "countryCode": "PG", "country": "Papua New Guinea" },
  { "countryCode": "PY", "country": "Paraguay" },
  { "countryCode": "PE", "country": "Peru" },
  { "countryCode": "PH", "country": "Philippines" },
  { "countryCode": "PN", "country": "Pitcairn Islands" },
  { "countryCode": "PL", "country": "Poland" },
  { "countryCode": "PT", "country": "Portugal" },
  { "countryCode": "XA", "country": "Pseudo-Accents" },
  { "countryCode": "XB", "country": "Pseudo-Bidi" },
  { "countryCode": "PR", "country": "Puerto Rico" },
  { "countryCode": "QA", "country": "Qatar" },
  { "countryCode": "RE", "country": "Réunion" },
  { "countryCode": "RO", "country": "Romania" },
  { "countryCode": "RU", "country": "Russia" },
  { "countryCode": "RW", "country": "Rwanda" },
  { "countryCode": "WS", "country": "Samoa" },
  { "countryCode": "SM", "country": "San Marino" },
  { "countryCode": "ST", "country": "São Tomé & Príncipe" },
  { "countryCode": "SA", "country": "Saudi Arabia" },
  { "countryCode": "SN", "country": "Senegal" },
  { "countryCode": "RS", "country": "Serbia" },
  { "countryCode": "SC", "country": "Seychelles" },
  { "countryCode": "SL", "country": "Sierra Leone" },
  { "countryCode": "SG", "country": "Singapore" },
  { "countryCode": "SX", "country": "Sint Maarten" },
  { "countryCode": "SK", "country": "Slovakia" },
  { "countryCode": "SI", "country": "Slovenia" },
  { "countryCode": "SB", "country": "Solomon Islands" },
  { "countryCode": "SO", "country": "Somalia" },
  { "countryCode": "ZA", "country": "South Africa" },
  { "countryCode": "GS", "country": "South Georgia & South Sandwich Islands" },
  { "countryCode": "KR", "country": "South Korea" },
  { "countryCode": "SS", "country": "South Sudan" },
  { "countryCode": "ES", "country": "Spain" },
  { "countryCode": "LK", "country": "Sri Lanka" },
  { "countryCode": "BL", "country": "St Barthélemy" },
  { "countryCode": "SH", "country": "St Helena" },
  { "countryCode": "KN", "country": "St Kitts & Nevis" },
  { "countryCode": "LC", "country": "St Lucia" },
  { "countryCode": "MF", "country": "St Martin" },
  { "countryCode": "PM", "country": "St Pierre & Miquelon" },
  { "countryCode": "VC", "country": "St Vincent & Grenadines" },
  { "countryCode": "SD", "country": "Sudan" },
  { "countryCode": "SR", "country": "Suriname" },
  { "countryCode": "SJ", "country": "Svalbard & Jan Mayen" },
  { "countryCode": "SE", "country": "Sweden" },
  { "countryCode": "CH", "country": "Switzerland" },
  { "countryCode": "SY", "country": "Syria" },
  { "countryCode": "TW", "country": "Taiwan" },
  { "countryCode": "TJ", "country": "Tajikistan" },
  { "countryCode": "TZ", "country": "Tanzania" },
  { "countryCode": "TH", "country": "Thailand" },
  { "countryCode": "TL", "country": "Timor-Leste" },
  { "countryCode": "TG", "country": "Togo" },
  { "countryCode": "TK", "country": "Tokelau" },
  { "countryCode": "TO", "country": "Tonga" },
  { "countryCode": "TT", "country": "Trinidad & Tobago" },
  { "countryCode": "TA", "country": "Tristan da Cunha" },
  { "countryCode": "TN", "country": "Tunisia" },
  { "countryCode": "TR", "country": "Turkey" },
  { "countryCode": "TM", "country": "Turkmenistan" },
  { "countryCode": "TC", "country": "Turks & Caicos Islands" },
  { "countryCode": "TV", "country": "Tuvalu" },
  { "countryCode": "UG", "country": "Uganda" },
  { "countryCode": "UA", "country": "Ukraine" },
  { "countryCode": "AE", "country": "United Arab Emirates" },
  { "countryCode": "GB", "country": "United Kingdom" },
  { "countryCode": "US", "country": "United States" },
  { "countryCode": "UY", "country": "Uruguay" },
  { "countryCode": "UM", "country": "US Outlying Islands" },
  { "countryCode": "VI", "country": "US Virgin Islands" },
  { "countryCode": "UZ", "country": "Uzbekistan" },
  { "countryCode": "VU", "country": "Vanuatu" },
  { "countryCode": "VA", "country": "Vatican City" },
  { "countryCode": "VE", "country": "Venezuela" },
  { "countryCode": "VN", "country": "Vietnam" },
  { "countryCode": "WF", "country": "Wallis & Futuna" },
  { "countryCode": "EH", "country": "Western Sahara" },
  { "countryCode": "YE", "country": "Yemen" },
  { "countryCode": "ZM", "country": "Zambia" },
  { "countryCode": "ZW", "country": "Zimbabwe" }
]
